fastapi_report/__init__.py
fastapi_report/cli.py
fastapi_report/models.py
fastapi_report/reporter.py
fastapi_report/discovery/__init__.py
fastapi_report/discovery/enum_detector.py
fastapi_report/discovery/fastapi_discovery.py
fastapi_report/discovery/mcp_discovery.py
fastapi_report/formatters/__init__.py
fastapi_report/formatters/base.py
fastapi_report/formatters/enum_formatter.py
fastapi_report/formatters/html_formatter.py
fastapi_report/formatters/json_formatter.py
fastapi_report/formatters/markdown_formatter.py
fastapi_report-1.0.2.dist-info/licenses/LICENSE
fastapi_report-1.0.2.dist-info/METADATA
fastapi_report-1.0.2.dist-info/WHEEL
fastapi_report-1.0.2.dist-info/entry_points.txt
fastapi_report-1.0.2.dist-info/top_level.txt
fastapi_report-1.0.2.dist-info/RECORD
