Metadata-Version: 2.4
Name: fastapi-report
Version: 1.0.2
Summary: Universal FastAPI documentation generator - automatically document REST endpoints and MCP tools
Home-page: https://github.com/maat16/fastapi-report
Author: FastAPI Report Contributors
Author-email: mahammad.suhail.94@gmail.com
License: MIT
Project-URL: Homepage, https://github.com/yourusername/fastapi-report
Project-URL: Documentation, https://github.com/yourusername/fastapi-report#readme
Project-URL: Repository, https://github.com/yourusername/fastapi-report
Project-URL: Bug Tracker, https://github.com/yourusername/fastapi-report/issues
Keywords: fastapi,documentation,openapi,mcp,api-documentation,swagger
Classifier: Development Status :: 5 - Production/Stable
Classifier: Intended Audience :: Developers
Classifier: Topic :: Software Development :: Documentation
Classifier: License :: OSI Approved :: MIT License
Classifier: Programming Language :: Python :: 3
Classifier: Programming Language :: Python :: 3.8
Classifier: Programming Language :: Python :: 3.9
Classifier: Programming Language :: Python :: 3.10
Classifier: Programming Language :: Python :: 3.11
Classifier: Programming Language :: Python :: 3.12
Classifier: Framework :: FastAPI
Requires-Python: >=3.8
License-File: LICENSE
Requires-Dist: fastapi>=0.100.0
Requires-Dist: pydantic>=2.0.0
Requires-Dist: requests>=2.28.0
Provides-Extra: dev
Requires-Dist: pytest>=7.0.0; extra == "dev"
Requires-Dist: pytest-cov>=4.0.0; extra == "dev"
Requires-Dist: hypothesis>=6.0.0; extra == "dev"
Requires-Dist: black>=23.0.0; extra == "dev"
Requires-Dist: flake8>=6.0.0; extra == "dev"
Requires-Dist: mypy>=1.0.0; extra == "dev"
Provides-Extra: mcp
Requires-Dist: fastapi-mcp>=0.1.0; extra == "mcp"
Dynamic: author-email
Dynamic: home-page
Dynamic: license-file
Dynamic: requires-python
